agent_lab_sdk/__init__.py
agent_lab_sdk/langgraph/checkpoint/__init__.py
agent_lab_sdk/langgraph/checkpoint/agw_saver.py
agent_lab_sdk/langgraph/checkpoint/serde.py
agent_lab_sdk/llm/__init__.py
agent_lab_sdk/llm/agw_token_manager.py
agent_lab_sdk/llm/gigachat_token_manager.py
agent_lab_sdk/llm/llm.py
agent_lab_sdk/llm/throttled.py
agent_lab_sdk/metrics/__init__.py
agent_lab_sdk/metrics/metrics.py
agent_lab_sdk/schema/__init__.py
agent_lab_sdk/schema/input_types.py
agent_lab_sdk/schema/log_message.py
agent_lab_sdk/storage/__init__.py
agent_lab_sdk/storage/storage.py
agent_lab_sdk/storage/storage_v2.py
agent_lab_sdk-0.1.50.dist-info/licenses/LICENSE
agent_lab_sdk-0.1.50.dist-info/METADATA
agent_lab_sdk-0.1.50.dist-info/WHEEL
agent_lab_sdk-0.1.50.dist-info/top_level.txt
agent_lab_sdk-0.1.50.dist-info/RECORD
