Metadata-Version: 2.4
Name: agent-lab-sdk
Version: 0.1.50
Summary: SDK для работы с Agent Lab
Author-email: Andrew Ohurtsov <andermirik@yandex.com>
License: Proprietary and Confidential — All Rights Reserved
Keywords: agent,lab,sdk
Classifier: Development Status :: 4 - Beta
Classifier: Intended Audience :: Developers
Classifier: Topic :: Software Development :: Libraries
Classifier: Topic :: Software Development :: Libraries :: Python Modules
Classifier: Programming Language :: Python :: 3
Classifier: Programming Language :: Python :: 3.11
Classifier: Programming Language :: Python :: 3.12
Classifier: Programming Language :: Python :: 3.13
Classifier: License :: Other/Proprietary License
Classifier: Operating System :: OS Independent
Requires-Python: <4.0,>=3.11
License-File: LICENSE
Requires-Dist: requests
Requires-Dist: langgraph
Requires-Dist: langchain_gigachat
Requires-Dist: prometheus-client
Requires-Dist: langchain
Requires-Dist: httpx
Requires-Dist: orjson
Requires-Dist: cloudpickle
Dynamic: license-file
